sql_cli/__init__.py
sql_cli/__main__.py
sql_cli/cli.py
sql_cli/configuration.py
sql_cli/connections.py
sql_cli/constants.py
sql_cli/dag_generator.py
sql_cli/exceptions.py
sql_cli/macros/tasks.py.jinja2
sql_cli/project.py
sql_cli/run_dag.py
sql_cli/sql_directory_parser.py
sql_cli/templates/dag.py.jinja2
sql_cli/utils/__init__.py
sql_cli/utils/airflow.py
sql_cli/utils/jinja.py
astro_run_command-0.1.1a0.dist-info/entry_points.txt
astro_run_command-0.1.1a0.dist-info/LICENSE
astro_run_command-0.1.1a0.dist-info/WHEEL
astro_run_command-0.1.1a0.dist-info/METADATA
astro_run_command-0.1.1a0.dist-info/RECORD
