Metadata-Version: 2.1
Name: astro-run-command
Version: 0.1.1a0
Summary: Empower analysts to build workflows to transform data using SQL
License: Apache-2.0
Keywords: sql,transform,analyst,workflow,airflow,astronomer
Author: Astronomer
Author-email: humans@astronomer.io
Requires-Python: >=3.7.1,<3.11
Classifier: Development Status :: 3 - Alpha
Classifier: Framework :: Apache Airflow
Classifier: License :: OSI Approved :: Apache Software License
Classifier: Programming Language :: Python :: 3
Classifier: Programming Language :: Python :: 3.8
Classifier: Programming Language :: Python :: 3.9
Classifier: Programming Language :: Python :: 3.10
Classifier: Programming Language :: Python :: 3
Classifier: Programming Language :: Python :: 3 :: Only
Classifier: Programming Language :: Python :: 3.10
Classifier: Programming Language :: Python :: 3.7
Classifier: Programming Language :: Python :: 3.8
Classifier: Programming Language :: Python :: 3.9
Classifier: Topic :: Database
Requires-Dist: Jinja2 (>=2.10.1,<=3.1)
Requires-Dist: PyYAML (>5.4.1)
Requires-Dist: apache-airflow (>2.0)
Requires-Dist: astro-sdk-python[all] (>=1.2.0,<2.0.0)
Requires-Dist: networkx (>=2.6.3,<3.0.0); python_version < "3.8"
Requires-Dist: networkx (>=2.8.7,<3.0.0); python_version >= "3.8"
Requires-Dist: python-dotenv (>=0.21.0,<0.22.0)
Requires-Dist: python-frontmatter (>=1.0.0,<2.0.0)
Requires-Dist: typer[all] (>=0.6.1,<0.7.0)
